LICENSE
MANIFEST.in
README.md
setup.json
setup.py
aiida_fireworks_scheduler/__init__.py
aiida_fireworks_scheduler/awareness.py
aiida_fireworks_scheduler/cmdline.py
aiida_fireworks_scheduler/common.py
aiida_fireworks_scheduler/fworker.py
aiida_fireworks_scheduler/fwscheduler.py
aiida_fireworks_scheduler/jobs.py
aiida_fireworks_scheduler.egg-info/PKG-INFO
aiida_fireworks_scheduler.egg-info/SOURCES.txt
aiida_fireworks_scheduler.egg-info/dependency_links.txt
aiida_fireworks_scheduler.egg-info/entry_points.txt
aiida_fireworks_scheduler.egg-info/requires.txt
aiida_fireworks_scheduler.egg-info/top_level.txt
aiida_fireworks_scheduler/scripts/__init__.py
aiida_fireworks_scheduler/scripts/arlaunch_run.py