Metadata-Version: 2.1
Name: aiida-fireworks-scheduler
Version: 1.0.0
Summary: AiiDA plugin to allow using `fireworks` as the execution engine for `CalcJob`.
Home-page: https://github.com/zhubonan/aiida-fireworks-scheduler
Author: Bonan Zhu
Author-email: zhubonan@outlook.com
License: MIT
Platform: UNKNOWN
Classifier: Programming Language :: Python
Classifier: Intended Audience :: Science/Research
Classifier: License :: OSI Approved :: MIT License
Classifier: Natural Language :: English
Classifier: Framework :: AiiDA
Provides-Extra: local
Provides-Extra: testing
Provides-Extra: pre-commit
Provides-Extra: docs
License-File: LICENSE
